finflow/__init__.py
finflow/src/__init__.py
finflow-0.1.0.dist-info/LICENSE
finflow-0.1.0.dist-info/WHEEL
finflow-0.1.0.dist-info/METADATA
finflow-0.1.0.dist-info/RECORD
