Metadata-Version: 2.1
Name: finflow
Version: 0.1.0
Summary: Modular pipelines to create and backtest investment strategies
License: MIT
Author: João Jacques
Author-email: joaopedro_jh@hotmail.com
Requires-Python: >=3.8,<4.0
Classifier: License :: OSI Approved :: MIT License
Classifier: Programming Language :: Python :: 3
Classifier: Programming Language :: Python :: 3.10
Classifier: Programming Language :: Python :: 3.8
Classifier: Programming Language :: Python :: 3.9
